{"abc": {"data1": "value1", "data2": "value2", "data3": "value3", "Time-To-Live": 5000, "CreatedAt": "2020-02-27T05:07:53.133320"}, "def": {"data1": "value1", "data2": "value2", "data3": "value3", "Time-To-Live": 50, "CreatedAt": "2020-02-27T05:07:53.133343"}, "jkl": {"data1": "value1", "data2": "value2", "data3": "value3", "Time-To-Live": 250, "CreatedAt": "2020-02-27T05:07:53.133359"}, "def3fdd2": {"dfdffs": "dasf", "Time-To-Live": 5000, "CreatedAt": "2020-02-27T14:36:16.093182"}, "def3f54544dd2": {"dfdffs": "dasf", "Time-To-Live": 50, "CreatedAt": "2020-02-27T14:36:50.719514"}}